ecomshared/__init__.py
ecomshared/apigateway.py
ecomshared/eventbridge.py
ecomshared/helpers.py
ecomshared/data/GetInventoryRequest.json
ecomshared/data/GetInventoryResponse.json
ecomshared/data/GetOrderRequest.json
ecomshared/data/GetOrderResponse.json
ecomshared/data/GetProductRequest.json
ecomshared/data/GetProductResponse.json
ecomshared/data/InventoryCreateRequest.json
ecomshared/data/InventoryUpdateRequest.json
ecomshared/data/InventoryUpdateResponse.json
ecomshared/data/InvoiceGenerateRequest.json
ecomshared/data/InvoiceGenerateResponse.json
ecomshared/data/Order.json
ecomshared/data/OrderCreateRequest.json
ecomshared/data/OrderItemDeliverySchedule.json
ecomshared/data/OrderItemPackageStatus.json
ecomshared/data/PackageShipped.json
ecomshared/data/PackagingStatusUpdate.json
ecomshared/data/PaymentProcessRequest.json
ecomshared/data/PaymentProcessResponse.json
ecomshared/data/RequisitionItemRelease.json
ecomshared/data/RequisitionItemRequest.json
ecomshared/data/RequisitionStatusUpdate.json
ecomshared/data/ScheduledOrderItem.json
ecomshared/data/TrackingGenerateRequest.json
ecomshared/data/TrackingGenerateResponse.json
ecomshared/data/UpdateOrderScheduleRequest.json
ecomshared/data/UpdateOrderScheduleResponse.json
ecomshared/data/ValidateInventoryItemRequest.json
ecomshared/data/ValidateInventoryItemResponse.json
ecomshared-0.2.8.dist-info/METADATA
ecomshared-0.2.8.dist-info/WHEEL
ecomshared-0.2.8.dist-info/top_level.txt
ecomshared-0.2.8.dist-info/RECORD
