Metadata-Version: 2.1
Name: ecomshared
Version: 0.2.8
Summary: UNKNOWN
Home-page: UNKNOWN
Author: Amazon Web Services
Author-email: UNKNOWN
License: MIT-0
Platform: UNKNOWN
Requires-Dist: boto3
